{
  "metadata": {
    "url": "https://www.labibliaexplicada.com/libro/libro-de-habacuc",
    "title": "Libro de Habacuc",
    "description": "El Libro de Habacuc es un diálogo profundo entre el profeta y Dios, donde se explora la fe en medio de la injusticia y el sufrimiento.",
    "ogImage": "https://cdn.prod.website-files.com/66cc37c6e520d3205900867a/670bf05c87bbd89e5c75c4f8_la-biblia-explicada.webp",
    "ogTitle": "Libro de Habacuc",
    "canonical": "https://www.labibliaexplicada.com/libro/libro-de-habacuc"
  },
  "templateType": "book",
  "templateClasses": {
    "body": "",
    "main": ""
  },
  "navigation": [
    {
      "href": "/conceptos-biblicos",
      "text": "Conceptos"
    },
    {
      "href": "/libros-de-la-biblia",
      "text": "Libros"
    },
    {
      "href": "/sobre-nosotros",
      "text": "Nosotros"
    },
    {
      "href": "/categoria/historia",
      "text": "Articulos"
    },
    {
      "href": "/categoria/curiosidades",
      "text": "Curiosidades y conceptos"
    },
    {
      "href": "/categoria/reflexiones-sobre-la-biblia",
      "text": "Reflexiones sobre La Biblia"
    }
  ],
  "images": [
    {
      "src": "https://cdn.prod.website-files.com/66cc37c5e520d320590085ca/66e720f973f65bd26a78f88b_Image.webp",
      "alt": ""
    },
    {
      "src": "https://cdn.prod.website-files.com/66cc37c5e520d320590085ca/66e72d69f63039a95e928cec_chevron-left.svg",
      "alt": "Volver a explorar el viaje"
    },
    {
      "src": "https://cdn.prod.website-files.com/66cc37c5e520d320590085ca/66e720f973f65bd26a78f88b_Image.webp",
      "alt": "La Biblia Explicada"
    }
  ],
  "structuredContent": {
    "bookName": "Libro de Habacuc",
    "description": "",
    "chapters": [
      {
        "href": "/capitulos/habacuc-1-habacuc-se-queja-de-injusticia",
        "text": "Habacuc se queja de injusticia"
      },
      {
        "href": "/capitulos/habacuc-2-jehova-responde-a-habacuc",
        "text": "Jehová responde a Habacuc"
      },
      {
        "href": "/capitulos/habacuc-3-oracion-de-habacuc",
        "text": "Oración de Habacuc"
      }
    ]
  },
  "cleanText": "ConceptosLibrosNosotrosLibro de HabacucLa BibliaLibro de HabacucCapítulos del libroHabacuc se queja de injusticiaJehová responde a HabacucOración de HabacucEl Libro de Habacuc nos presenta una conversación íntima y profunda entre el profeta y Dios. Habacuc, al observar la violencia y la injusticia que prevalecían en su nación, no puede evitar levantar su voz en un clamor de duda. Es un hombre fiel, pero también es sincero en su relación con Dios, y en ese diálogo vemos algo que muchos de nosotros hemos sentido: el deseo de entender por qué el mal parece prevalecer, por qué la justicia parece ausente.Este profeta, a diferencia de muchos otros, no se limita a entregar un mensaje; más bien, es un ejemplo vivo de cómo llevar nuestras inquietudes más profundas ante Dios. Habacuc se pregunta por qué Dios permite la corrupción en su propio pueblo, y más allá de eso, por qué Dios usaría a una nación aún más perversa, como Babilonia, para ejecutar su juicio. Aquí está una de las grandes tensiones del libro: ¿cómo puede un Dios justo usar a los malvados para castigar a otros?En su duda, sin embargo, Habacuc recibe una respuesta divina. Dios le revela que, aunque el mal parece reinar, no durará para siempre. Los malvados también recibirán su juicio en su debido tiempo. La paciencia de Dios no es un signo de debilidad o indiferencia, sino parte de su plan perfecto que a veces se escapa de nuestra comprensión humana. Aquí es donde surge una de las declaraciones más poderosas del Antiguo Testamento: “el justo vivirá por su fe”. Es una llamada a confiar en Dios, no solo cuando las cosas son claras, sino especialmente cuando son confusas. Esta declaración tiene eco a lo largo de la historia bíblica y se convierte en un pilar de la enseñanza cristiana, recordándonos que la fe es la respuesta ante lo inexplicable.El camino de la fe que propone Habacuc no es fácil. Es un caminar en la oscuridad, confiando en que Dios, en su tiempo, traerá la luz. Habacuc no recibe todas las respuestas que busca, pero sí recibe una visión más amplia: Dios está obrando, y aunque la justicia no sea inmediata, llegará. Este mensaje resuena a lo largo de las Escrituras, y es citado por Pablo en sus cartas a los Romanos y Gálatas, donde se destaca que la verdadera vida no se encuentra en las circunstancias exteriores, sino en la fe en Dios.Lo que hace único al libro de Habacuc es que no termina con una queja, sino con una hermosa proclamación de confianza. En el capítulo tres, Habacuc entona un himno que expresa una entrega total a la voluntad de Dios. “Aunque la higuera no florezca, ni en las vides haya fruto… con todo, yo me alegraré en el Señor”. Este es un testimonio de fe madura, una fe que no depende de las circunstancias, sino de la convicción profunda de que Dios es soberano y bueno, incluso cuando no entendemos sus caminos. Aquí, Habacuc nos muestra que, aunque no tengamos el control, podemos tener la certeza de que Dios sí lo tiene, y eso es suficiente.El libro también nos recuerda una lección importante sobre el tiempo divino. Habacuc anhelaba una justicia rápida, pero Dios le mostró que su plan abarca más que los deseos inmediatos de los seres humanos. El juicio vendría, pero en el momento adecuado, y mientras tanto, el justo debía mantenerse firme, viviendo por su fe. Esta paciencia en Dios es un acto de resistencia frente a la desesperación, una invitación a confiar incluso cuando la solución parece lejana.Finalmente, Habacuc nos enseña a transformar nuestras preguntas y frustraciones en oración. Su diálogo con Dios es un modelo de cómo podemos acercarnos a nuestro Creador, con respeto pero también con honestidad. A través de esa conversación, Habacuc encuentra paz, no porque haya recibido todas las respuestas, sino porque ha sido recordado de la fidelidad de Dios a lo largo del tiempo.A lo largo del Libro de Habacuc, se nos invita a enfrentar nuestras propias dudas con fe. En un mundo donde la injusticia y el sufrimiento parecen dominar, Habacuc nos recuerda que la historia no ha terminado. La justicia divina vendrá, y mientras esperamos, nuestra tarea es vivir confiados en el Señor, sabiendo que, en su momento, todo será puesto en su lugar. Es un llamado a tener una fe que ve más allá de las circunstancias y se apoya en el carácter inmutable de Dios.ANTERIORLibro de NahumSIGUIENTELibro de SofoníasGénesisÉxodoLevíticoLibro de los NúmerosDeuteronomioLibro de JosuéLibro de los JuecesLibro de RutI SamuelII SamuelI ReyesII ReyesI CrónicasII CrónicasLibro de EsdrasLibro de NehemíasLibro de EsterLibro de JobLibro de los SalmosProverbiosLibro del EclesiastésCantar de los CantaresLibro de IsaíasLibro de JeremíasLibro de las LamentacionesLibro de EzequielLibro de DanielLibro de OseasLibro de JoelLibro de AmósLibro de AbdíasLibro de JonásLibro de MiqueasLibro de HabacucLibro de HageoLibro de ZacaríasLibro de MalaquíasEvangelio de MateoEvangelio de MarcosEvangelio de LucasEvangelio de JuanHechos de los ApóstolesEpístola a los romanosPrimera epí"
}