{
  "metadata": {
    "url": "https://www.labibliaexplicada.com/libro/libro-de-los-jueces",
    "title": "Libro de los Jueces",
    "description": "El Libro de los Jueces narra la constante lucha de Israel por mantenerse fiel a Dios, mostrando el ciclo de redención a través de líderes levantados en tiempos de crisis.",
    "ogImage": "https://cdn.prod.website-files.com/66cc37c6e520d3205900867a/670bf05c87bbd89e5c75c4f8_la-biblia-explicada.webp",
    "ogTitle": "Libro de los Jueces",
    "canonical": "https://www.labibliaexplicada.com/libro/libro-de-los-jueces"
  },
  "templateType": "book",
  "templateClasses": {
    "body": "",
    "main": ""
  },
  "navigation": [
    {
      "href": "/conceptos-biblicos",
      "text": "Conceptos"
    },
    {
      "href": "/libros-de-la-biblia",
      "text": "Libros"
    },
    {
      "href": "/sobre-nosotros",
      "text": "Nosotros"
    },
    {
      "href": "/categoria/historia",
      "text": "Articulos"
    },
    {
      "href": "/categoria/curiosidades",
      "text": "Curiosidades y conceptos"
    },
    {
      "href": "/categoria/reflexiones-sobre-la-biblia",
      "text": "Reflexiones sobre La Biblia"
    }
  ],
  "images": [
    {
      "src": "https://cdn.prod.website-files.com/66cc37c5e520d320590085ca/66e720f973f65bd26a78f88b_Image.webp",
      "alt": ""
    },
    {
      "src": "https://cdn.prod.website-files.com/66cc37c5e520d320590085ca/66e72d69f63039a95e928cec_chevron-left.svg",
      "alt": "Volver a explorar el viaje"
    },
    {
      "src": "https://cdn.prod.website-files.com/66cc37c5e520d320590085ca/66e720f973f65bd26a78f88b_Image.webp",
      "alt": "La Biblia Explicada"
    }
  ],
  "structuredContent": {
    "bookName": "Libro de los Jueces",
    "description": "",
    "chapters": [
      {
        "href": "/capitulos/jueces-1-juda-y-simeon-capturan-a-adoni-bezec",
        "text": "Judá y Simeón capturan a Adoni-bezec"
      },
      {
        "href": "/capitulos/jueces-2-el-angel-de-jehova-en-boquim",
        "text": "El ángel de Jehová en Boquim"
      },
      {
        "href": "/capitulos/jueces-3-naciones-que-fueron-dejadas-para-probar-a-israel",
        "text": "Naciones que fueron dejadas para probar a Israel"
      },
      {
        "href": "/capitulos/jueces-4-debora-y-barac-derrotan-a-sisara",
        "text": "Débora y Barac derrotan a Sísara"
      },
      {
        "href": "/capitulos/jueces-5-cantico-de-debora-y-de-barac",
        "text": "Cántico de Débora y de Barac"
      },
      {
        "href": "/capitulos/jueces-6-llamamiento-de-gedeon",
        "text": "Llamamiento de Gedeón"
      },
      {
        "href": "/capitulos/jueces-7-gedeon-derrota-a-los-madianitas",
        "text": "Gedeón derrota a los madianitas"
      },
      {
        "href": "/capitulos/jueces-8-gedeon-captura-a-los-reyes-de-madian",
        "text": "Gedeón captura a los reyes de Madián"
      },
      {
        "href": "/capitulos/jueces-9-reinado-de-abimelec",
        "text": "Reinado de Abimelec"
      },
      {
        "href": "/capitulos/jueces-10-tola-y-jair-juzgan-a-israel",
        "text": "Tola y Jair juzgan a Israel"
      },
      {
        "href": "/capitulos/jueces-11",
        "text": "Libro de los Jueces 11"
      },
      {
        "href": "/capitulos/jueces-12-ibzan-elon-y-abdon-jueces-de-israel",
        "text": "Ibzán, Elón y Abdón, jueces de Israel"
      },
      {
        "href": "/capitulos/jueces-13-nacimiento-de-sanson",
        "text": "Nacimiento de Sansón"
      },
      {
        "href": "/capitulos/jueces-14-sanson-y-la-mujer-filistea-de-timnat",
        "text": "Sansón y la mujer filistea de Timnat"
      },
      {
        "href": "/capitulos/jueces-15-sanson-derrota-a-los-filisteos-en-lehi",
        "text": "Sansón derrota a los filisteos en Lehi"
      },
      {
        "href": "/capitulos/jueces-16-sanson-en-gaza",
        "text": "Sansón en Gaza"
      },
      {
        "href": "/capitulos/jueces-17-las-imagenes-y-el-sacerdote-de-micaia",
        "text": "Las imágenes y el sacerdote de Micaía"
      },
      {
        "href": "/capitulos/jueces-18-micaia-y-los-hombres-de-dan",
        "text": "Micaía y los hombres de Dan"
      },
      {
        "href": "/capitulos/jueces-19-el-levita-y-su-concubina",
        "text": "El levita y su concubina"
      },
      {
        "href": "/capitulos/jueces-20-la-guerra-contra-benjamin",
        "text": "La guerra contra Benjamín"
      },
      {
        "href": "/capitulos/jueces-21-mujeres-para-los-benjaminitas",
        "text": "Mujeres para los benjaminitas"
      }
    ]
  },
  "cleanText": "ConceptosLibrosNosotrosLibro de los JuecesLa BibliaLibro de los JuecesCapítulos del libroJudá y Simeón capturan a Adoni-bezecEl ángel de Jehová en BoquimNaciones que fueron dejadas para probar a IsraelDébora y Barac derrotan a SísaraCántico de Débora y de BaracLlamamiento de GedeónGedeón derrota a los madianitasGedeón captura a los reyes de MadiánReinado de AbimelecTola y Jair juzgan a IsraelLibro de los Jueces 11Ibzán, Elón y Abdón, jueces de IsraelNacimiento de SansónSansón y la mujer filistea de TimnatSansón derrota a los filisteos en LehiSansón en GazaLas imágenes y el sacerdote de MicaíaMicaía y los hombres de DanEl levita y su concubinaLa guerra contra BenjamínMujeres para los benjaminitasEl Libro de los Jueces se estructura alrededor de un ciclo repetitivo donde el pueblo de Israel se aleja de Dios, experimenta opresión y luego clama por ayuda. Este ciclo es una ilustración poderosa de la naturaleza humana, que tiende a olvidar a Dios cuando las cosas van bien, pero vuelve a Él en tiempos de necesidad. Es un recordatorio constante de la fidelidad de Dios frente a la infidelidad humana.Los jueces no eran jueces en el sentido moderno, sino líderes militares y espirituales que guiaban al pueblo de Israel en tiempos de crisis. Aunque el término puede llevarnos a pensar en tribunales, en realidad, estos jueces eran guerreros, profetas y libertadores que respondían al clamor del pueblo.Un ejemplo notable es el de Débora, una mujer que sobresalió en un tiempo patriarcal. No solo fue jueza, sino también profetisa, liderando a Israel hacia la victoria en la batalla contra Sísara. Su historia es un recordatorio del poder de Dios para levantar líderes inesperados, incluso en una cultura dominada por hombres.Por otro lado, Gedeón, otro juez destacado, es conocido por su vacilación. A diferencia de otros líderes, Gedeón pidió varias señales a Dios para confirmar su llamado. Esto revela que Dios a menudo elige a personas que dudan de sí mismas, pero que confían en Él a pesar de sus inseguridades.El libro también refleja el conflicto interno en Israel. A pesar de ser un pueblo elegido, las tribus de Israel no siempre actuaron en unidad, lo que provocó conflictos entre ellas. Esta división interna es un preludio de las luchas que surgirían más tarde en la historia de Israel, durante la época de los reyes.Sansón es, sin duda, uno de los jueces más conocidos por su fuerza, pero su historia es también un recordatorio de cómo la falta de disciplina espiritual puede llevar a la destrucción. Aunque tenía un don físico extraordinario, su debilidad espiritual lo llevó a la traición de Dalila y, finalmente, a su caída.Uno de los episodios más trágicos del libro es el de Jefté, quien hizo un voto precipitado. Después de ganar la batalla, tuvo que cumplir su promesa de sacrificar lo primero que saliera de su casa, que resultó ser su propia hija. Este relato es un poderoso recordatorio de la importancia de ser cuidadosos con nuestras promesas, especialmente cuando se trata de Dios.La frase “cada uno hacía lo que bien le parecía” es una de las más recurrentes en el libro. Refleja una época de anarquía, donde la falta de un liderazgo central llevó a la decadencia moral y espiritual de la nación. Israel estaba en un estado de caos, sin un rey que los guiara.El libro también muestra la lucha constante de Israel por mantenerse fiel a Dios en medio de las influencias paganas. Las naciones vecinas, con sus dioses y costumbres, continuamente alejaban al pueblo de la verdadera adoración. Este desafío refleja la lucha de la humanidad por mantener su fidelidad a Dios en medio de las distracciones del mundo.Finalmente, el Libro de los Jueces anticipa el deseo de Israel por tener un rey. La falta de un liderazgo fuerte y constante llevó al pueblo a anhelar un rey que los guiara y los protegiera de sus enemigos. Esta necesidad prepara el terreno para la monarquía que se establecerá en los libros siguientes.El Libro de los Jueces nos deja muchas lecciones. Nos habla de la fidelidad de Dios incluso cuando Su pueblo se desvía, de cómo el Señor levanta a personas inesperadas para cumplir Su propósito, y de los peligros de vivir sin una guía clara. Al final, el libro es un recordatorio de nuestra necesidad constante de buscar a Dios en todas las etapas de nuestra vida, reconociendo que, incluso en medio del caos, Su misericordia siempre está presente.ANTERIORLibro de JosuéSIGUIENTELibro de RutGénesisÉxodoLevíticoLibro de los NúmerosDeuteronomioLibro de los JuecesI SamuelII SamuelI ReyesII ReyesI CrónicasII CrónicasLibro de EsdrasLibro de NehemíasLibro de EsterLibro de JobLibro de los SalmosProverbiosLibro del EclesiastésCantar de los CantaresLibro de IsaíasLibro de JeremíasLibro de las LamentacionesLibro de EzequielLibro de DanielLibro de OseasLibro de JoelLibro de AmósLibro de AbdíasLibro de JonásLibro de MiqueasLibro de NahumLibro de HabacucLibro de SofoníasLibro de HageoLibro de ZacaríasLibro de MalaquíasEvangelio de MateoEvangelio de MarcosEv"
}