{
  "metadata": {
    "url": "https://www.labibliaexplicada.com/libro/epistola-a-los-hebreos",
    "title": "Epístola a los hebreos",
    "description": "La Epístola a los hebreos revela la superioridad de Cristo como Sumo Sacerdote y Salvador, llamando a la fe y perseverancia.",
    "ogImage": "https://cdn.prod.website-files.com/66cc37c6e520d3205900867a/670bf05c87bbd89e5c75c4f8_la-biblia-explicada.webp",
    "ogTitle": "Epístola a los hebreos",
    "canonical": "https://www.labibliaexplicada.com/libro/epistola-a-los-hebreos"
  },
  "templateType": "book",
  "templateClasses": {
    "body": "",
    "main": ""
  },
  "navigation": [
    {
      "href": "/conceptos-biblicos",
      "text": "Conceptos"
    },
    {
      "href": "/libros-de-la-biblia",
      "text": "Libros"
    },
    {
      "href": "/sobre-nosotros",
      "text": "Nosotros"
    },
    {
      "href": "/categoria/historia",
      "text": "Articulos"
    },
    {
      "href": "/categoria/curiosidades",
      "text": "Curiosidades y conceptos"
    },
    {
      "href": "/categoria/reflexiones-sobre-la-biblia",
      "text": "Reflexiones sobre La Biblia"
    }
  ],
  "images": [
    {
      "src": "https://cdn.prod.website-files.com/66cc37c5e520d320590085ca/66e720f973f65bd26a78f88b_Image.webp",
      "alt": ""
    },
    {
      "src": "https://cdn.prod.website-files.com/66cc37c5e520d320590085ca/66e72d69f63039a95e928cec_chevron-left.svg",
      "alt": "Volver a explorar el viaje"
    },
    {
      "src": "https://cdn.prod.website-files.com/66cc37c5e520d320590085ca/66e720f973f65bd26a78f88b_Image.webp",
      "alt": "La Biblia Explicada"
    }
  ],
  "structuredContent": {
    "bookName": "Epístola a los hebreos",
    "description": "",
    "chapters": [
      {
        "href": "/capitulos/hebreos-1-dios-ha-hablado-por-su-hijo",
        "text": "Dios ha hablado por su Hijo"
      },
      {
        "href": "/capitulos/hebreos-2-una-salvacion-tan-grande",
        "text": "Una salvación tan grande"
      },
      {
        "href": "/capitulos/hebreos-3-jesus-es-superior-a-moises",
        "text": "Jesús es superior a Moisés"
      },
      {
        "href": "/capitulos/hebreos-4-jesus-el-gran-sumo-sacerdote",
        "text": "Jesús el gran sumo sacerdote"
      },
      {
        "href": "/capitulos/hebreos-5-advertencia-contra-la-apostasia",
        "text": "Advertencia contra la apostasía"
      },
      {
        "href": "/capitulos/hebreos-6",
        "text": "Epístola a los hebreos 6"
      },
      {
        "href": "/capitulos/hebreos-7-el-sacerdocio-de-melquisedec",
        "text": "El sacerdocio de Melquisedec"
      },
      {
        "href": "/capitulos/hebreos-8-el-mediador-de-un-nuevo-pacto",
        "text": "El mediador de un nuevo pacto"
      },
      {
        "href": "/capitulos/hebreos-9-el-sacrificio-de-cristo-quita-el-pecado",
        "text": "El sacrificio de Cristo quita el pecado"
      },
      {
        "href": "/capitulos/hebreos-10-advertencia-al-que-peca-deliberadamente",
        "text": "Advertencia al que peca deliberadamente"
      },
      {
        "href": "/capitulos/hebreos-11-la-fe",
        "text": "La fe"
      },
      {
        "href": "/capitulos/hebreos-12-puestos-los-ojos-en-jesus",
        "text": "Puestos los ojos en Jesús"
      },
      {
        "href": "/capitulos/hebreos-13-deberes-cristianos",
        "text": "Deberes cristianos"
      }
    ]
  },
  "cleanText": "ConceptosLibrosNosotrosEpístola a los hebreosLa BibliaEpístola a los hebreosCapítulos del libroDios ha hablado por su HijoUna salvación tan grandeJesús es superior a MoisésJesús el gran sumo sacerdoteAdvertencia contra la apostasíaEpístola a los hebreos 6El sacerdocio de MelquisedecEl mediador de un nuevo pactoEl sacrificio de Cristo quita el pecadoAdvertencia al que peca deliberadamenteLa fePuestos los ojos en JesúsDeberes cristianosLa Epístola a los hebreos es un libro que invita a contemplar profundamente la superioridad de Cristo sobre todo lo que el pueblo de Dios conocía antes. A pesar de no saber con certeza quién la escribió, lo que sí sabemos es que fue inspirada para una comunidad de creyentes judíos que luchaban con su fe en medio de las dificultades. ¿Qué hacer cuando parece más fácil volver a lo conocido, en lugar de caminar hacia lo nuevo que Cristo ofrece?Una de las figuras más intrigantes que aparece en este libro es Melquisedec, un sacerdote enigmático que se presenta como un modelo de Jesús: sin principio ni fin, eterno. Este es solo un ejemplo de cómo Hebreos teje las promesas del Antiguo Testamento y las lleva a su cumplimiento en Cristo. Aquí, Jesús no es solo un profeta más, es el Sumo Sacerdote definitivo, quien se ofreció a sí mismo una vez por todas, logrando la redención que los antiguos sacrificios no podían.La fe ocupa un lugar central en esta carta. Piensa en aquellos héroes bíblicos mencionados en el capítulo 11, quienes, sin ver el cumplimiento de las promesas, creyeron. Este es un recordatorio hermoso de que la fe es la confianza en lo que no vemos, pero sabemos que es cierto.El descanso también tiene un nuevo significado. No es solo la entrada a la Tierra Prometida, sino la entrada a la paz eterna en Dios. Este descanso es una promesa viva para nosotros hoy, una invitación a confiar en Cristo como el camino seguro hacia la vida eterna.El lenguaje de la Epístola a los hebreos está lleno de simbolismo del templo y los sacrificios, pero todo apunta a una sola verdad: en Cristo, encontramos el cumplimiento de todo lo que Dios ha planeado. Así que no dejes que las dificultades te desvíen. Cristo es más grande que cualquier desafío. Él es el sumo sacerdote que intercede por nosotros en el cielo, y en Él podemos encontrar descanso y confianza.Hebreos es una llamada a permanecer firmes, a no volver atrás, sino a avanzar con la certeza de que Jesús ya ha hecho el camino. Mantengamos la fe y avancemos hacia esa promesa de descanso eterno, sabiendo que nuestro sumo sacerdote vive para interceder por nosotros.ANTERIOREpístola a FilemónSIGUIENTEEpístola de SantiagoGénesisÉxodoLevíticoLibro de los NúmerosDeuteronomioLibro de JosuéLibro de los JuecesLibro de RutI SamuelII SamuelI ReyesII ReyesI CrónicasII CrónicasLibro de EsdrasLibro de NehemíasLibro de EsterLibro de JobLibro de los SalmosProverbiosLibro del EclesiastésCantar de los CantaresLibro de IsaíasLibro de JeremíasLibro de las LamentacionesLibro de EzequielLibro de DanielLibro de OseasLibro de JoelLibro de AmósLibro de AbdíasLibro de JonásLibro de MiqueasLibro de NahumLibro de HabacucLibro de SofoníasLibro de HageoLibro de ZacaríasLibro de MalaquíasEvangelio de MateoEvangelio de MarcosEvangelio de LucasEvangelio de JuanHechos de los ApóstolesEpístola a los romanosPrimera epístola a los corintiosSegunda epístola a los corintiosEpístola a los gálatasEpístola a los efesiosEpístola a los filipensesEpístola a los colosensesPrimera epístola a los tesalonicensesSegunda epístola a los tesalonicensesPrimera epístola a TimoteoSegunda epístola a TimoteoEpístola a TitoEpístola a los hebreosPrimera epístola de PedroSegunda epístola de PedroPrimera epístola de JuanSegunda epístola de JuanTercera epístola de JuanEpístola de JudasApocalipsisMas LIBROsApocalipsisEpístola de JudasTercera epístola de JuanSegunda epístola de JuanPrimera epístola de JuanSegunda epístola de PedroPrimera epístola de PedroEpístola de SantiagoEpístola a los hebreosEpístola a FilemónEpístola a TitoSegunda epístola a TimoteoPrimera epístola a TimoteoSegunda epístola a los tesalonicensesPrimera epístola a los tesalonicensesEpístola a los colosensesEpístola a los filipensesEpístola a los efesiosEpístola a los gálatasSegunda epístola a los corintiosPrimera epístola a los corintiosEpístola a los romanosHechos de los ApóstolesEvangelio de JuanEvangelio de LucasEvangelio de MarcosEvangelio de MateoLibro de MalaquíasLibro de ZacaríasLibro de HageoLibro de SofoníasLibro de HabacucLibro de NahumLibro de MiqueasLibro de JonásLibro de AbdíasLibro de AmósLibro de JoelLibro de OseasLibro de DanielLibro de EzequielLibro de las LamentacionesLibro de JeremíasLibro de IsaíasLibro del EclesiastésProverbiosLibro de los SalmosLibro de JobLibro de EsterLibro de NehemíasLibro de EsdrasII CrónicasI CrónicasII ReyesI ReyesII SamuelI SamuelLibro de los JuecesLibro de JosuéDeuteronomioLibro de los NúmerosLevíticoÉxodoCantar de los CantaresGénesisLibro de Rut2025 LA biblia explicadaCategoryArticulosCu"
}