{
  "metadata": {
    "url": "https://www.labibliaexplicada.com/articulos/7-mujeres-poderosas-del-antiguo-testamento-sus-historias",
    "title": "7 Mujeres Poderosas del Antiguo Testamento: Sus Historias",
    "description": "Explora las historias de siete mujeres poderosas del Antiguo Testamento que transformaron sus comunidades con fe y valentía.",
    "ogImage": "https://cdn.prod.website-files.com/66cc37c6e520d3205900867a/6822451fe0de4eed627cd875_7%20Mujeres%20Poderosas%20del%20Antiguo%20Testamento.jpg",
    "ogTitle": "7 Mujeres Poderosas del Antiguo Testamento: Sus Historias",
    "canonical": "https://www.labibliaexplicada.com/articulos/7-mujeres-poderosas-del-antiguo-testamento-sus-historias"
  },
  "templateType": "article",
  "templateClasses": {
    "body": "",
    "main": ""
  },
  "navigation": [
    {
      "href": "/conceptos-biblicos",
      "text": "Conceptos"
    },
    {
      "href": "/libros-de-la-biblia",
      "text": "Libros"
    },
    {
      "href": "/sobre-nosotros",
      "text": "Nosotros"
    },
    {
      "href": "/categoria/historia",
      "text": "Articulos"
    },
    {
      "href": "/categoria/curiosidades",
      "text": "Curiosidades y conceptos"
    },
    {
      "href": "/categoria/reflexiones-sobre-la-biblia",
      "text": "Reflexiones sobre La Biblia"
    }
  ],
  "images": [
    {
      "src": "https://cdn.prod.website-files.com/66cc37c5e520d320590085ca/66e720f973f65bd26a78f88b_Image.webp",
      "alt": ""
    },
    {
      "src": "https://cdn.prod.website-files.com/66cc37c6e520d3205900867a/6822451fe0de4eed627cd875_7%20Mujeres%20Poderosas%20del%20Antiguo%20Testamento.jpg",
      "alt": ""
    },
    {
      "src": "https://cdn.prod.website-files.com/66cc37c6e520d3205900867a/68c968fd3553b0da9d5a9cbd_Charlie%20Kirk.jpg",
      "alt": ""
    },
    {
      "src": "https://cdn.prod.website-files.com/66cc37c6e520d3205900867a/68c948c65c3576e2b498d5b7_Evidencia%20arqueolo%CC%81gica%20del%20legado%20de%20Babel%20%20.jpg",
      "alt": ""
    },
    {
      "src": "https://cdn.prod.website-files.com/66cc37c5e520d320590085ca/66e720f973f65bd26a78f88b_Image.webp",
      "alt": "La Biblia Explicada"
    }
  ],
  "structuredContent": {
    "headline": "7 Mujeres Poderosas del Antiguo Testamento: Sus Historias",
    "author": "EstherEstherByEstherByEstherByEstherByEsther",
    "date": "",
    "categories": [],
    "body": "<div data-collapse=\"medium\" data-animation=\"default\" data-duration=\"400\" data-easing=\"ease\" data-easing2=\"ease\" role=\"banner\" class=\"navigation w-nav\"><div class=\"navigation-container\"><a href=\"/\" class=\"logo w-inline-block\"><img src=\"https://cdn.prod.website-files.com/66cc37c5e520d320590085ca/66e720f973f65bd26a78f88b_Image.webp\" width=\"Auto\" sizes=\"(max-width: 1024px) 100vw, 1024px\" srcset=\"https://cdn.prod.website-files.com/66cc37c5e520d320590085ca/66e720f973f65bd26a78f88b_Image-p-500.webp 500w, https://cdn.prod.website-files.com/66cc37c5e520d320590085ca/66e720f973f65bd26a78f88b_Image-p-800.webp 800w, https://cdn.prod.website-files.com/66cc37c5e520d320590085ca/66e720f973f65bd26a78f88b_Image.webp 1024w\" alt=\"\" class=\"image-logo\"></a><nav role=\"navigation\" class=\"nav-menu w-nav-menu\"><a href=\"/conceptos-biblicos\" class=\"navigation-link w-inline-block\"><div class=\"navigation-link-text\">Conceptos</div><div class=\"navigation-hover\" style=\"opacity: 0; height: 0px;\"></div></a><a href=\"/libros-de-la-biblia\" class=\"navigation-link w-inline-block\"><div class=\"navigation-link-text\">Libros</div><div class=\"navigation-hover\" style=\"opacity: 0; height: 0px;\"></div></a><a href=\"/sobre-nosotros\" class=\"navigation-link w-inline-block\"><div class=\"navigation-link-text\">Nosotros</div><div class=\"navigation-hover\" style=\"opacity: 0; height: 0px;\"></div></a></nav><form action=\"/search\" class=\"search w-form\"><input class=\"search-input w-input\" maxlength=\"256\" name=\"query\" placeholder=\"Qué deseas saber?\" type=\"search\" id=\"search\" required=\"\"><input type=\"submit\" class=\"search-button w-button\" value=\"Buscar\"></form><div class=\"menu-button w-nav-button\" style=\"-webkit-user-select: text;\" aria-label=\"menu\" role=\"button\" tabindex=\"0\" aria-controls=\"w-nav-overlay-0\" aria-haspopup=\"menu\" aria-expanded=\"false\"><div class=\"icon-2 w-icon-nav-menu\"></div></div></div><div class=\"w-nav-overlay\" data-wf-ignore=\"\" id=\"w-nav-overlay-0\"></div></div><div class=\"title-section\"><div data-w-id=\"c8f0aa1d-e0ec-8d59-bb5a-ab5abae6eecd\" style=\"transform: translate3d(0px, 1.0911px, 0px) scale3d(1, 1, 1) rotateX(0deg) rotateY(0deg) rotateZ(0deg) skew(0deg, 0deg); opacity: 0.96363; transform-style: preserve-3d; will-change: opacity, transform;\" class=\"container cc-center\"><div class=\"text-container\"><a href=\"/categoria/curiosidades\" class=\"section-title-text w-inline-block\"><div class=\"post-category-text\">Curiosidades y conceptos</div></a><h1 class=\"h1\">7 Mujeres Poderosas del Antiguo Testamento: Sus Historias</h1><div class=\"post-author-text cc-center\"><div style=\"background-image:url(&quot;https://cdn.prod.website-files.com/66cc37c6e520d3205900867a/66cc37c6e520d320590086fb_4.jpg&quot;)\" class=\"author-image-wrapper\"></div><a href=\"/autores/esther\" class=\"post-author\">Esther</a></div></div></div></div><div class=\"post-image\"><div class=\"container cc-post-image\"><img alt=\"\" src=\"https://cdn.prod.website-files.com/66cc37c6e520d3205900867a/6822451fe0de4eed627cd875_7%20Mujeres%20Poderosas%20del%20Antiguo%20Testamento.jpg\" sizes=\"100vw\" srcset=\"https://cdn.prod.website-files.com/66cc37c6e520d3205900867a/6822451fe0de4eed627cd875_7%20Mujeres%20Poderosas%20del%20Antiguo%20Testamento-p-500.jpg 500w, https://cdn.prod.website-files.com/66cc37c6e520d3205900867a/6822451fe0de4eed627cd875_7%20Mujeres%20Poderosas%20del%20Antiguo%20Testamento-p-800.jpg 800w, https://cdn.prod.website-files.com/66cc37c6e520d3205900867a/6822451fe0de4eed627cd875_7%20Mujeres%20Poderosas%20del%20Antiguo%20Testamento-p-1080.jpg 1080w, https://cdn.prod.website-files.com/66cc37c6e520d3205900867a/6822451fe0de4eed627cd875_7%20Mujeres%20Poderosas%20del%20Antiguo%20Testamento-p-1600.jpg 1600w, https://cdn.prod.website-files.com/66cc37c6e520d3205900867a/6822451fe0de4eed627cd875_7%20Mujeres%20Poderosas%20del%20Antiguo%20Testamento-p-2000.jpg 2000w, https://cdn.prod.website-files.com/66cc37c6e520d3205900867a/6822451fe0de4eed627cd875_7%20Mujeres%20Poderosas%20del%20Antiguo%20Testamento-p-2600.jpg 2600w, https://cdn.prod.website-files.com/66cc37c6e520d3205900867a/6822451fe0de4eed627cd875_7%20Mujeres%20Poderosas%20del%20Antiguo%20Testamento.jpg 2752w\" class=\"post-image-full-width\"></div></div><div class=\"post-content\"><div class=\"post-content-wrapper\"><div class=\"rich-text w-richtext\"><div class=\"w-embed w-iframe\"><h1 id=\"7-mujeres-poderosas-del-antiguo-testamento-sus-historias\" tabindex=\"-1\">7 Mujeres Poderosas del Antiguo Testamento: Sus Historias</h1>\n<p><strong>¿Sabías que algunas mujeres del Antiguo Testamento cambiaron el curso de la historia con su fe, valentía y sabiduría?</strong> Aquí te presentamos a siete figuras clave que dejaron una huella imborrable en los relatos bíblicos:</p>\n<ul>\n<li><strong>Débora</strong>: Jueza y profetisa que lideró a Israel hacia la victoria y 40 años de paz.</li>\n<li><strong>Ester</strong>: Reina que arriesgó su vida para salvar al pueblo judío.</li>\n<li><strong>Rut</strong>: Un ejemplo de lealtad, cuya fe la llevó a formar parte del linaje de Jesús.</li>\n<li><strong>Ana</strong>: Mujer de oración que confió en Dios y fue madre del profeta Samuel.</li>\n<li><strong>Rahab</strong>: Una mujer valiente que protegió a los espías israelitas y se unió al plan divino.</li>\n<li><strong>Abigail</strong>: Con sabiduría y diplomacia, evitó un conflicto que pudo ser fatal.</li>\n<li><strong>Miriam</strong>: Hermana de Moisés y primera profetisa, guía espiritual del pueblo de Israel.</li>\n</ul>\n<p>Estas historias nos enseñan que la fe y las decisiones valientes pueden transformar vidas y comunidades. Sigue leyendo para descubrir cómo estas mujeres marcaron la diferencia en su tiempo y cómo su legado sigue siendo una fuente de inspiración hoy.</p>\n<h2 id=\"historias-de-mujeres-extraordinarias-en-la-biblia-debora-rut-ester-y-maria\" tabindex=\"-1\">Historias de mujeres extraordinarias en la Biblia: Débora, Rut, Ester y María</h2>\n<iframe class=\"sb-iframe\" src=\"https://www.youtube.com/embed/1dzgRGb1nRU\" frameborder=\"0\" loading=\"lazy\" allowfullscreen=\"\" style=\"width: 100%; height: auto; aspect-ratio: 16/9;\"></iframe><h2 id=\"1-debora-jueza-y-profetisa\" tabindex=\"-1\">1. Débora: Jueza y Profetisa</h2>\n<p>Débora fue la única mujer que ejerció como jueza en Israel, destacándose como una figura clave tanto espiritual como política durante 20 años de opresión bajo el reinado de Jabín, rey de Canaán <a href=\"https://www.gotquestions.org/Espanol/Debora-en-la-Biblia.html\" target=\"_blank\" style=\"text-decoration: none;\"><sup>[1]</sup></a>. Su tribunal, situado bajo una palmera entre Ramá y Betel, representaba su cercanía al pueblo y su rol como guía espiritual <a href=\"https://margmowczko.com/espanol/mujeres-de-la-biblia-con-autoridad-espiritual/\" target=\"_blank\" style=\"text-decoration: none;\"><sup>[2]</sup></a>.</p>\n<p>Débora recibió un mandato divino que transmitió a Barac, instruyéndolo a liberar a Israel. Además, anunció que la victoria no sería atribuida a él, sino que llegaría a través de una mujer. Como se registra:</p>\n<blockquote>\n<p>\"Si tú vas conmigo, yo iré; pero si no vas conmigo, no iré... sin embargo, no será tuya la gloria de la jornada que emprendes, pues Jehová entregará a Sísara en manos de una mujer\" <a href=\"https://www.gotquestions.org/Espanol/Debora-en-la-Biblia.html\" target=\"_blank\" style=\"text-decoration: none;\"><sup>[1]</sup></a><a href=\"https://www.bibliaon.com/es/historia_de_debora/\" target=\"_blank\" style=\"text-decoration: none;\"><sup>[3]</sup></a>.</p>\n</blockquote>\n<p>La profecía se cumplió cuando Débora, junto a Barac, lideró una victoria decisiva sobre Sísara, que culminó con la intervención de Jael <a href=\"https://www.gotquestions.org/Espanol/Debora-en-la-Biblia.html\" target=\"_blank\" style=\"text-decoration: none;\"><sup>[1]</sup></a>. Este triunfo permitió que Israel disfrutara de 40 años de paz <a href=\"https://www.bibliaon.com/es/historia_de_debora/\" target=\"_blank\" style=\"text-decoration: none;\"><sup>[3]</sup></a>. El \"Cántico de Débora\" (Jueces 5), uno de los poemas más antiguos de la Biblia, celebra esta liberación.</p>\n<p>Débora dejó un legado que demuestra cómo el liderazgo puede combinar autoridad espiritual con la capacidad de inspirar a otros hacia un objetivo común <a href=\"https://margmowczko.com/espanol/mujeres-de-la-biblia-con-autoridad-espiritual/\" target=\"_blank\" style=\"text-decoration: none;\"><sup>[2]</sup></a><a href=\"https://www.bibliaon.com/es/historia_de_debora/\" target=\"_blank\" style=\"text-decoration: none;\"><sup>[3]</sup></a>. Su valentía y fe la convierten en un ejemplo, junto a otras mujeres del Antiguo Testamento, que marcaron la historia bíblica de manera duradera.</p>\n<h2 id=\"2-esther-reina-y-libertadora\" tabindex=\"-1\">2. Esther: Reina y Libertadora</h2>\n<p>Esther, una joven judía que llegó a ser reina de Persia, tuvo un papel clave en la salvación de su pueblo durante el reinado del rey Asuero (Jerjes I). Siguiendo el consejo de su primo Mardoqueo, decidió mantener en secreto que era judía, una elección que resultó decisiva cuando Amán, un alto funcionario, planeó eliminar a los judíos.</p>\n<p>El momento más crítico de su historia llegó cuando Mardoqueo le advirtió sobre el peligro que enfrentaba su pueblo. Sus palabras fueron un llamado directo al valor y la acción:</p>\n<blockquote>\n<p>\"¿Y quién sabe si para este tiempo has llegado al reino?\"</p>\n</blockquote>\n<p>Antes de actuar, Esther mostró su fe organizando tres días de ayuno y oración. Con valentía y astucia, se presentó ante el rey y logró revertir el decreto que amenazaba a su pueblo.</p>\n<p>Su coraje es recordado en la celebración de <a href=\"https://es.wikipedia.org/wiki/Purim\" target=\"_blank\">Purim</a>, que conmemora su papel en la liberación de los judíos. La historia de Esther es un ejemplo de cómo alguien puede usar una posición de poder para proteger a los demás, demostrando que el verdadero liderazgo implica estar dispuesto a actuar en beneficio de otros.</p>\n<p>Así como Esther defendió a su pueblo, otras mujeres del Antiguo Testamento también mostraron cómo la fe y las decisiones valientes pueden cambiar el curso de los acontecimientos.</p>\n<h2 id=\"3-ruth-modelo-de-lealtad\" tabindex=\"-1\">3. Ruth: Modelo de Lealtad</h2>\n<p>Ruth, una mujer moabita casada con uno de los hijos de Noemí, enfrentó una decisión difícil tras la muerte de su esposo. En un acto de profunda lealtad y fe, decidió quedarse al lado de su suegra, dejando atrás su tierra natal y sus creencias para seguir la fe de Israel.</p>\n<p>Con una declaración que marcó su vida, Ruth expresó su compromiso:</p>\n<blockquote>\n<p>\"A donde tú vayas, yo iré, y donde tú vivas, yo viviré. Tu pueblo será mi pueblo, y tu Dios será mi Dios.\"</p>\n</blockquote>\n<p>Ruth no solo habló de su lealtad, sino que la demostró con hechos. Trabajó arduamente en los campos de Booz para sostenerse a sí misma y a Noemí. Su dedicación llamó la atención de Booz, quien finalmente se casó con ella, asegurando un futuro estable para ambas. Ruth llegó a ser bisabuela de David y forma parte del linaje de Jesús, según se menciona en el Evangelio de Mateo 1:5.</p>\n<p>Su historia nos enseña que la grandeza no siempre se encuentra en posiciones de poder, sino en los actos cotidianos de fidelidad y servicio. Ruth nos recuerda cómo la fe y la dedicación pueden transformar vidas y dejar un impacto duradero.</p>\n<p>Al igual que Ruth, muchas otras mujeres en la Biblia dejaron un legado de valentía y devoción que sigue inspirando hasta hoy.</p>\n<h2 id=\"4-ana-mujer-de-oracion\" tabindex=\"-1\">4. Ana: Mujer de Oración</h2>\n<p>Ana es un ejemplo poderoso de fe y perseverancia en la oración en el Antiguo Testamento. Su historia, narrada en 1 Samuel 1-2, describe a una mujer que enfrentó el dolor de no poder tener hijos.</p>\n<p>Aunque su esposo Elcaná la amaba profundamente y le daba una porción especial en las ofrendas anuales en Siló, Ana sufría intensamente. Su dolor se intensificaba por las constantes burlas de Penina, la otra esposa de Elcaná.</p>\n<p>En medio de su angustia, Ana mostró una fe firme a través de la oración. En el templo de Siló, oró con tal fervor que el sacerdote Elí pensó que estaba ebria. Su plegaria fue un reflejo de su confianza y entrega a Dios:</p>\n<blockquote>\n<p>\"O Lord Almighty, if you will look down upon my sorrow and answer my prayer and give me a son, then I will give him back to you. He will be yours for his entire lifetime.\"</p>\n</blockquote>\n<p>Ana no solo oró con claridad y propósito, sino que también entregó su mayor deseo a Dios, confiando plenamente en Su respuesta. Dios escuchó su oración y le concedió un hijo, Samuel, quien se convertiría en uno de los grandes profetas de Israel.</p>\n<p>El cántico de Ana en 1 Samuel 2:1-10 es un testimonio de su fe profunda y de su comprensión de la obra de Dios. Es una de las oraciones más hermosas y significativas del Antiguo Testamento:</p>\n<blockquote>\n<p>\"Mi corazón se regocija en el Señor; en el Señor mi poder se exalta. Mi boca se ríe de mis enemigos, porque me alegro en tu salvación.\"</p>\n</blockquote>\n<p>La historia de Ana nos recuerda que la oración constante y una fe sincera pueden cambiar incluso las situaciones más difíciles. Su ejemplo, al igual que el de otras mujeres del Antiguo Testamento, muestra cómo la fe puede influir en decisiones importantes y transformar vidas.</p>\n<h6 id=\"sbb-itb-0f3dda6\" tabindex=\"-1\">sbb-itb-0f3dda6</h6>\n<h2 id=\"5-rahab-protectora-de-israel\" tabindex=\"-1\">5. Rahab: Protectora de Israel</h2>\n<p>Rahab, una mujer de Jericó, es recordada por su valentía y fe al proteger a los espías israelitas, jugando un papel clave en la conquista de la Tierra Prometida. Su historia, narrada en el libro de Josué, muestra cómo alguien ajeno al pueblo de Israel se convirtió en parte del plan de Dios.</p>\n<p>Rahab demostró gran discernimiento y confianza al reconocer el poder del Dios de Israel. Cuando dos espías israelitas llegaron a Jericó, ella no solo les ofreció refugio, sino que también los protegió de las autoridades locales con inteligencia y determinación. Su declaración de fe es poderosa:</p>\n<blockquote>\n<p>\"Sé que el Señor les ha dado esta tierra... porque el Señor su Dios es Dios arriba en los cielos y abajo en la tierra.\"</p>\n</blockquote>\n<p>Estas palabras reflejan su comprensión del poder de Dios y su decisión de unirse a Su propósito.</p>\n<p>Su fe no se quedó en palabras. Rahab actuó con valentía al esconder a los espías y negociar la salvación de su familia. Siguiendo las instrucciones, colocó un cordón escarlata en su ventana como señal, asegurando la protección de los suyos.</p>\n<p>Rahab sigue siendo un ejemplo de fe activa. Su inclusión en la genealogía de Jesús en Mateo 1:5 resalta su papel en la historia de la salvación. Su historia demuestra cómo la fe puede cambiar vidas y tener impacto en generaciones. Su valentía y determinación la convierten en un modelo de acción basada en convicciones.</p>\n<p>El libro de Hebreos 11:31 la menciona como una mujer cuya fe la separó de los desobedientes, mostrando cómo confiar en Dios puede transformar vidas y comunidades.</p>\n<p>Al igual que Rahab, muchas otras mujeres del Antiguo Testamento mostraron cómo la confianza en Dios puede alterar el curso de la historia.</p>\n<h2 id=\"6-abigail-voz-de-la-razon\" tabindex=\"-1\">6. Abigail: Voz de la Razón</h2>\n<p>Abigail se destaca en el Antiguo Testamento como un ejemplo de sabiduría y discernimiento. En 1 Samuel 25, se la describe como \"una mujer hermosa y de buen entendimiento\" <a href=\"https://www.socialsellinator.com/social-selling-blog/seo-article-writing\" target=\"_blank\" style=\"text-decoration: none;\"><sup>[5]</sup></a>.</p>\n<p>Su historia ocurre en un momento crucial, cuando su esposo Nabal insulta gravemente a David, el futuro rey de Israel. En lugar de quedarse al margen ante el peligro inminente, Abigail toma la iniciativa con rapidez y claridad.</p>\n<p>Preparó una ofrenda generosa para David y sus hombres, demostrando no solo generosidad, sino también astucia y comprensión del propósito divino de David. Según el relato bíblico:</p>\n<blockquote>\n<p>\"Ella se apresuró a preparar doscientos panes, dos odres de vino, cinco ovejas guisadas, cinco medidas de grano tostado, cien racimos de uvas pasas y doscientos panes de higos secos\" - 1 Samuel 25:18</p>\n</blockquote>\n<p>Este acto no solo apaciguó la ira de David, sino que también evidenció su capacidad para tomar decisiones estratégicas en situaciones críticas.</p>\n<p>La historia de Abigail subraya cómo la sabiduría se traduce en acciones valientes y efectivas. Su habilidad para resolver conflictos y su disposición a actuar con determinación muestran cómo decisiones acertadas pueden cambiar el rumbo de los acontecimientos, incluso en circunstancias difíciles.</p>\n<p>Al igual que Abigail, otras mujeres del Antiguo Testamento también desempeñaron papeles cruciales en momentos decisivos, dejando un legado de liderazgo y valentía.</p>\n<h2 id=\"7-miriam-hermana-de-moises-y-lider\" tabindex=\"-1\">7. Miriam: Hermana de Moisés y Líder</h2>\n<p>Miriam, reconocida como la primera profetisa en la Biblia, destacó por su valentía desde temprana edad al proteger a su hermano Moisés <a href=\"https://es.wikipedia.org/wiki/Ana_(madre_de_Samuel)\" target=\"_blank\" style=\"text-decoration: none;\"><sup>[4]</sup></a>. Mientras él flotaba en una cesta sobre el río Nilo, su determinación aseguró la supervivencia de quien más tarde se convertiría en el libertador de Israel.</p>\n<p>Su papel como líder se hizo evidente tras el cruce del Mar Rojo, como se relata en Éxodo 15:20-21:</p>\n<blockquote>\n<p>\"Entonces Miriam la profetisa, hermana de Aarón, tomó un pandero en su mano, y todas las mujeres salieron en pos de ella con panderos y danzas\" - Éxodo 15:20</p>\n</blockquote>\n<p>Guiaba a las mujeres israelitas en momentos de celebración y también en tiempos difíciles. Su influencia espiritual no se limitó a los cantos de victoria, sino que también se manifestó durante la travesía por el desierto, marcando un ejemplo de fortaleza y guía.</p>\n<p>Sin embargo, no estuvo exenta de desafíos. En un momento, junto con Aarón, cuestionó el liderazgo de Moisés debido a su matrimonio con una mujer cusita. Este incidente resalta la importancia de mantener la humildad, incluso en roles de liderazgo.</p>\n<p>El legado de Miriam ilustra cómo la fe y el coraje pueden influir en el destino de una comunidad. Su vida nos enseña que liderar no solo implica fortaleza espiritual, sino también la capacidad de inspirar y guiar en cualquier circunstancia, ya sea en la alegría o en la adversidad.</p>\n<p>Miriam, al igual que otras mujeres del Antiguo Testamento, dejó una huella imborrable con su liderazgo y fe.</p>\n<h2 id=\"conclusion\" tabindex=\"-1\">Conclusión</h2>\n<p>Miriam, junto a otras mujeres del Antiguo Testamento, dejó un legado de fe, sabiduría y liderazgo que sigue resonando más allá de su tiempo y contexto. Estas historias muestran que la influencia espiritual y el impacto en la comunidad no están limitados por género o posición social.</p>\n<p>Cada una de ellas marcó una diferencia en su entorno: Ana con su perseverancia en la oración, Débora con su capacidad para liderar, Ester al intervenir para salvar a su pueblo y Rut con su lealtad inquebrantable. Abigail resolvió conflictos con inteligencia, Rahab mostró una fe valiente, y Miriam destacó como una guía espiritual. Sus vidas siguen siendo fuente de inspiración.</p>\n<p>Estas mujeres nos enseñan que la verdadera fortaleza nace de una conexión profunda con lo divino. Sus ejemplos nos invitan a:</p>\n<ul>\n<li>Mantener una vida de oración y actuar con integridad en momentos clave.</li>\n<li>Liderar con sabiduría y humildad.</li>\n<li>Ser leales y perseverantes frente a las dificultades.</li>\n</ul>\n<p>El impacto de su fe activa transformó familias, comunidades e incluso naciones. Sus historias nos recuerdan que la grandeza espiritual se refleja en una fe vivida con valentía y principios sólidos.</p>\n<p>Reflexionar sobre sus vidas nos anima a enfrentar nuestros propios retos con determinación y a ser agentes de cambio en nuestras comunidades, demostrando que una fe vivida con propósito puede dejar una huella duradera.</p>\n<h2 id=\"faqs\" tabindex=\"-1\">FAQs</h2>\n<h3 id=\"que-mujeres-destacadas-aparecen-en-el-antiguo-testamento\" tabindex=\"-1\">¿Qué mujeres destacadas aparecen en el Antiguo Testamento?</h3>\n<p>El Antiguo Testamento menciona a siete mujeres que dejaron una huella profunda en la historia bíblica gracias a su fe y liderazgo:</p>\n<ul>\n<li>\n<p><strong>Débora</strong>: Jueza y profetisa que condujo a Israel a la victoria, mostrando una gran sabiduría (Jueces 4-5).</p>\n</li>\n<li>\n<p><strong>Ester</strong>: Reina que arriesgó su vida para salvar a su pueblo, utilizando su posición con valentía.</p>\n</li>\n<li>\n<p><strong>Rut</strong>: Ejemplo de lealtad, cuya decisión de seguir a Dios la llevó a ser antepasada del rey David.</p>\n</li>\n<li>\n<p><strong>Ana</strong>: Su oración constante y fe inquebrantable quedaron reflejadas en su cántico:</p>\n<blockquote>\n<p>\"Mi corazón se alegra en Jehová, mi fuerza se levanta en Jehová; mi boca se ensanchó sobre mis enemigos, porque me alegré en tu salvación.\"</p>\n</blockquote>\n</li>\n<li>\n<p><strong>Rahab</strong>: Protegió a los espías israelitas y, gracias a su fe, pasó a formar parte del linaje del Mesías.</p>\n</li>\n<li>\n<p><strong>Abigail</strong>: Con sabiduría y diplomacia, evitó un conflicto que pudo haber tenido consecuencias graves.</p>\n</li>\n<li>\n<p><strong>Miriam</strong>: Profetisa y líder que, junto a sus hermanos, guió al pueblo de Israel durante el éxodo.</p>\n</li>\n</ul>\n<p>Estas mujeres desafiaron las normas de su tiempo, demostrando que el liderazgo espiritual no está limitado por género. Sus historias siguen siendo relevantes y enseñan cómo la fe y el valor pueden impactar tanto a individuos como a comunidades enteras.</p></div></div></div></div><div class=\"separator\"><div class=\"separator-container\"><div class=\"line-color\"></div></div></div><div class=\"latest-posts\"><div class=\"container\"><div class=\"section-title-text\">articulos recientes</div><div class=\"posts-wrapper\"><div class=\"posts-collection-list-wrapper w-dyn-list\"><div role=\"list\" class=\"posts-collection-list w-dyn-items w-row\"><div role=\"listitem\" class=\"_2-collection-item w-dyn-item w-col w-col-6\"><a href=\"/articulos/continua-la-busqueda-del-sospechoso-del-asesinato-de-charlie-kirk\" class=\"posts-image w-inline-block\"><img alt=\"\" src=\"https://cdn.prod.website-files.com/66cc37c6e520d3205900867a/68c968fd3553b0da9d5a9cbd_Charlie%20Kirk.jpg\" sizes=\"(max-width: 479px) 96vw, (max-width: 767px) 97vw, (max-width: 991px) 48vw, 50vw\" srcset=\"https://cdn.prod.website-files.com/66cc37c6e520d3205900867a/68c968fd3553b0da9d5a9cbd_Charlie%20Kirk-p-500.jpg 500w, https://cdn.prod.website-files.com/66cc37c6e520d3205900867a/68c968fd3553b0da9d5a9cbd_Charlie%20Kirk-p-800.jpg 800w, https://cdn.prod.website-files.com/66cc37c6e520d3205900867a/68c968fd3553b0da9d5a9cbd_Charlie%20Kirk.jpg 1024w\" class=\"post_miniature\"></a><div class=\"post-info-text\"><a href=\"/categoria/historia\" class=\"category-link\">Articulos</a><a href=\"/articulos/continua-la-busqueda-del-sospechoso-del-asesinato-de-charlie-kirk\" class=\"post-title w-inline-block\"><h2 class=\"h3\">Continúa la búsqueda del sospechoso del asesinato de Charlie Kirk</h2></a><div class=\"post-author-text cc-small-thumbnail\"><div class=\"post-author cc-top-margin\">By</div><a href=\"/autores/esther\" class=\"post-author\">Esther</a></div></div></div><div role=\"listitem\" class=\"_2-collection-item w-dyn-item w-col w-col-6\"><a href=\"/articulos/evidencia-arqueologica-del-legado-de-babel\" class=\"posts-image w-inline-block\"><img alt=\"\" src=\"https://cdn.prod.website-files.com/66cc37c6e520d3205900867a/68c948c65c3576e2b498d5b7_Evidencia%20arqueolo%CC%81gica%20del%20legado%20de%20Babel%20%20.jpg\" sizes=\"(max-width: 479px) 96vw, (max-width: 767px) 97vw, (max-width: 991px) 48vw, 50vw\" srcset=\"https://cdn.prod.website-files.com/66cc37c6e520d3205900867a/68c948c65c3576e2b498d5b7_Evidencia%20arqueolo%CC%81gica%20del%20legado%20de%20Babel%20%20-p-500.jpg 500w, https://cdn.prod.website-files.com/66cc37c6e520d3205900867a/68c948c65c3576e2b498d5b7_Evidencia%20arqueolo%CC%81gica%20del%20legado%20de%20Babel%20%20-p-800.jpg 800w, https://cdn.prod.website-files.com/66cc37c6e520d3205900867a/68c948c65c3576e2b498d5b7_Evidencia%20arqueolo%CC%81gica%20del%20legado%20de%20Babel%20%20.jpg 1024w\" class=\"post_miniature\"></a><div class=\"post-info-text\"><a href=\"/categoria/historia\" class=\"category-link\">Articulos</a><a href=\"/articulos/evidencia-arqueologica-del-legado-de-babel\" class=\"post-title w-inline-block\"><h2 class=\"h3\">Evidencia arqueológica del legado de Babel</h2></a><div class=\"post-author-text cc-small-thumbnail\"><div class=\"post-author cc-top-margin\">By</div><a href=\"/autores/esther\" class=\"post-author\">Esther</a></div></div></div></div></div></div></div></div><div class=\"footer\"><div class=\"container-footer\"><div class=\"container\"><div class=\"top-section\"><a href=\"#\" class=\"logo cc-footer w-inline-block\"><img src=\"https://cdn.prod.website-files.com/66cc37c5e520d320590085ca/66e720f973f65bd26a78f88b_Image.webp\" sizes=\"(max-width: 1024px) 100vw, 1024px\" srcset=\"https://cdn.prod.website-files.com/66cc37c5e520d320590085ca/66e720f973f65bd26a78f88b_Image-p-500.webp 500w, https://cdn.prod.website-files.com/66cc37c5e520d320590085ca/66e720f973f65bd26a78f88b_Image-p-800.webp 800w, https://cdn.prod.website-files.com/66cc37c5e520d320590085ca/66e720f973f65bd26a78f88b_Image.webp 1024w\" alt=\"La Biblia Explicada\" class=\"image-logo\"></a><div class=\"footer-small-text\">2025 LA biblia explicada</div></div></div><div class=\"separator-footer\"><div class=\"separator-color footer-line\"></div></div><div class=\"container\"><div class=\"bottom\"><div class=\"bottom-1\"><div data-delay=\"0\" data-hover=\"false\" class=\"dropdown w-dropdown\"><div class=\"dropdown-toggle w-dropdown-toggle\" id=\"w-dropdown-toggle-0\" aria-controls=\"w-dropdown-list-0\" aria-haspopup=\"menu\" aria-expanded=\"false\" role=\"button\" tabindex=\"0\"><div class=\"icon w-icon-dropdown-toggle\" aria-hidden=\"true\"></div><div>Category</div></div><nav class=\"dropdown-list w-dropdown-list\" id=\"w-dropdown-list-0\" aria-labelledby=\"w-dropdown-toggle-0\"><div class=\"w-dyn-list\"><div role=\"list\" class=\"w-dyn-items\"><div role=\"listitem\" class=\"dropdown-link w-dyn-item\"><a href=\"/categoria/historia\" class=\"dropdown-link-text\" tabindex=\"0\">Articulos</a></div><div role=\"listitem\" class=\"dropdown-link w-dyn-item\"><a href=\"/categoria/curiosidades\" class=\"dropdown-link-text\" tabindex=\"0\">Curiosidades y conceptos</a></div><div role=\"listitem\" class=\"dropdown-link w-dyn-item\"><a href=\"/categoria/reflexiones-sobre-la-biblia\" class=\"dropdown-link-text\" tabindex=\"0\">Reflexiones sobre La Biblia</a></div></div></div></nav></div><div class=\"footer-categories\"><div class=\"footer-title-text\">CATEGORIAS</div><div class=\"footer-links-container cc-categories\"><div class=\"w-dyn-list\"><div role=\"list\" class=\"collection-list w-dyn-items\"><div role=\"listitem\" class=\"footer-collection-item w-dyn-item\"><a href=\"/categoria/historia\" class=\"link-footer\">Articulos</a></div><div role=\"listitem\" class=\"footer-collection-item w-dyn-item\"><a href=\"/categoria/curiosidades\" class=\"link-footer\">Curiosidades y conceptos</a></div><div role=\"listitem\" class=\"footer-collection-item w-dyn-item\"><a href=\"/categoria/reflexiones-sobre-la-biblia\" class=\"link-footer\">Reflexiones sobre La Biblia</a></div></div></div></div></div><div class=\"footer-newsletter\"></div></div><div class=\"bottom-2\"><div class=\"footer-links-container\"><div class=\"footer-links\"></div></div></div></div></div></div></div><!-- Google tag (gtag.js) -->\n\n"
  },
  "cleanText": "ConceptosLibrosNosotrosCuriosidades y conceptos7 Mujeres Poderosas del Antiguo Testamento: Sus HistoriasEsther7 Mujeres Poderosas del Antiguo Testamento: Sus Historias ¿Sabías que algunas mujeres del Antiguo Testamento cambiaron el curso de la historia con su fe, valentía y sabiduría? Aquí te presentamos a siete figuras clave que dejaron una huella imborrable en los relatos bíblicos: Débora: Jueza y profetisa que lideró a Israel hacia la victoria y 40 años de paz. Ester: Reina que arriesgó su vida para salvar al pueblo judío. Rut: Un ejemplo de lealtad, cuya fe la llevó a formar parte del linaje de Jesús. Ana: Mujer de oración que confió en Dios y fue madre del profeta Samuel. Rahab: Una mujer valiente que protegió a los espías israelitas y se unió al plan divino. Abigail: Con sabiduría y diplomacia, evitó un conflicto que pudo ser fatal. Miriam: Hermana de Moisés y primera profetisa, guía espiritual del pueblo de Israel. Estas historias nos enseñan que la fe y las decisiones valientes pueden transformar vidas y comunidades. Sigue leyendo para descubrir cómo estas mujeres marcaron la diferencia en su tiempo y cómo su legado sigue siendo una fuente de inspiración hoy. Historias de mujeres extraordinarias en la Biblia: Débora, Rut, Ester y María 1. Débora: Jueza y Profetisa Débora fue la única mujer que ejerció como jueza en Israel, destacándose como una figura clave tanto espiritual como política durante 20 años de opresión bajo el reinado de Jabín, rey de Canaán [1]. Su tribunal, situado bajo una palmera entre Ramá y Betel, representaba su cercanía al pueblo y su rol como guía espiritual [2]. Débora recibió un mandato divino que transmitió a Barac, instruyéndolo a liberar a Israel. Además, anunció que la victoria no sería atribuida a él, sino que llegaría a través de una mujer. Como se registra: \"Si tú vas conmigo, yo iré; pero si no vas conmigo, no iré... sin embargo, no será tuya la gloria de la jornada que emprendes, pues Jehová entregará a Sísara en manos de una mujer\" [1][3]. La profecía se cumplió cuando Débora, junto a Barac, lideró una victoria decisiva sobre Sísara, que culminó con la intervención de Jael [1]. Este triunfo permitió que Israel disfrutara de 40 años de paz [3]. El \"Cántico de Débora\" (Jueces 5), uno de los poemas más antiguos de la Biblia, celebra esta liberación. Débora dejó un legado que demuestra cómo el liderazgo puede combinar autoridad espiritual con la capacidad de inspirar a otros hacia un objetivo común [2][3]. Su valentía y fe la convierten en un ejemplo, junto a otras mujeres del Antiguo Testamento, que marcaron la historia bíblica de manera duradera. 2. Esther: Reina y Libertadora Esther, una joven judía que llegó a ser reina de Persia, tuvo un papel clave en la salvación de su pueblo durante el reinado del rey Asuero (Jerjes I). Siguiendo el consejo de su primo Mardoqueo, decidió mantener en secreto que era judía, una elección que resultó decisiva cuando Amán, un alto funcionario, planeó eliminar a los judíos. El momento más crítico de su historia llegó cuando Mardoqueo le advirtió sobre el peligro que enfrentaba su pueblo. Sus palabras fueron un llamado directo al valor y la acción: \"¿Y quién sabe si para este tiempo has llegado al reino?\" Antes de actuar, Esther mostró su fe organizando tres días de ayuno y oración. Con valentía y astucia, se presentó ante el rey y logró revertir el decreto que amenazaba a su pueblo. Su coraje es recordado en la celebración de Purim, que conmemora su papel en la liberación de los judíos. La historia de Esther es un ejemplo de cómo alguien puede usar una posición de poder para proteger a los demás, demostrando que el verdadero liderazgo implica estar dispuesto a actuar en beneficio de otros. Así como Esther defendió a su pueblo, otras mujeres del Antiguo Testamento también mostraron cómo la fe y las decisiones valientes pueden cambiar el curso de los acontecimientos. 3. Ruth: Modelo de Lealtad Ruth, una mujer moabita casada con uno de los hijos de Noemí, enfrentó una decisión difícil tras la muerte de su esposo. En un acto de profunda lealtad y fe, decidió quedarse al lado de su suegra, dejando atrás su tierra natal y sus creencias para seguir la fe de Israel. Con una declaración que marcó su vida, Ruth expresó su compromiso: \"A donde tú vayas, yo iré, y donde tú vivas, yo viviré. Tu pueblo será mi pueblo, y tu Dios será mi Dios.\" Ruth no solo habló de su lealtad, sino que la demostró con hechos. Trabajó arduamente en los campos de Booz para sostenerse a sí misma y a Noemí. Su dedicación llamó la atención de Booz, quien finalmente se casó con ella, asegurando un futuro estable para ambas. Ruth llegó a ser bisabuela de David y forma parte del linaje de Jesús, según se menciona en el Evangelio de Mateo 1:5. Su historia nos enseña que la grandeza no siempre se encuentra en posiciones de poder, sino en los actos cotidianos de fidelidad y servicio. Ruth nos recuerda cómo la fe y la dedicación pueden transformar vidas y dejar un impacto durad"
}